README.md
setup.py
riffdog/__init__.py
riffdog/command_line.py
riffdog/config.py
riffdog/data_structures.py
riffdog/exceptions.py
riffdog/resource.py
riffdog/scanner.py
riffdog.egg-info/PKG-INFO
riffdog.egg-info/SOURCES.txt
riffdog.egg-info/dependency_links.txt
riffdog.egg-info/entry_points.txt
riffdog.egg-info/requires.txt
riffdog.egg-info/top_level.txt
riffdog/resources/__init__.py