Metadata-Version: 2.1
Name: riffdog
Version: 0.1.0
Summary: Terraform - Reality Scanner
Home-page: https://github.com/riffdog/riffdog
Author: James Taylor
Author-email: jtaylor@cpicardgroup.com
License: MIT
Keywords: terraform aws coverage
Platform: UNKNOWN
Classifier: Development Status :: 4 - Beta
Classifier: Intended Audience :: Developers
Classifier: Intended Audience :: System Administrators
Classifier: Topic :: System :: Installation/Setup
Classifier: Topic :: System :: Monitoring
Classifier: Topic :: System :: Systems Administration
Classifier: License :: OSI Approved :: MIT License
Classifier: Programming Language :: Python :: 3
Classifier: Programming Language :: Python :: 3.5
Classifier: Programming Language :: Python :: 3.6
Classifier: Programming Language :: Python :: 3.7
Provides-Extra: aws
